zenodozipdownloader/__init__.py
zenodozipdownloader/__main__.py
zenodozipdownloader/_version.py
zenodozipdownloader/core.py
zenodozipdownloader-0.1.0a1.dist-info/licenses/LICENSE
zenodozipdownloader-0.1.0a1.dist-info/METADATA
zenodozipdownloader-0.1.0a1.dist-info/WHEEL
zenodozipdownloader-0.1.0a1.dist-info/entry_points.txt
zenodozipdownloader-0.1.0a1.dist-info/top_level.txt
zenodozipdownloader-0.1.0a1.dist-info/RECORD
