Metadata-Version: 2.4
Name: zenodozipdownloader
Version: 0.1.0a1
Summary: Download and extract (single) files from ZIP archives in Zenodo records.
Author-email: Jan Christoph Thiele <jan.thiele@chem.ox.ac.uk>
License-Expression: MIT
Project-URL: Homepage, https://github.com/thielec/zenodozipdownloader
Keywords: zenodo,zip,downloader,zenodo-zip
Classifier: Development Status :: 4 - Beta
Classifier: Intended Audience :: Science/Research
Classifier: Programming Language :: Python :: 3
Classifier: Programming Language :: Python :: 3 :: Only
Classifier: Programming Language :: Python :: 3.10
Classifier: Topic :: Software Development :: Libraries
Classifier: Topic :: Scientific/Engineering
Requires-Python: >=3.10
License-File: LICENSE
Requires-Dist: requests>=2.28
Requires-Dist: urllib3~=2.5.0
Requires-Dist: remotezip
Provides-Extra: tqdm
Requires-Dist: tqdm; extra == "tqdm"
Provides-Extra: dev
Requires-Dist: pre-commit; extra == "dev"
Requires-Dist: black; extra == "dev"
Dynamic: license-file
